{"word": "confirm", "main_definition": "To establish the truth or correctness of something, usually by providing evidence or additional information.", "meanings_and_examples": [{"definition": "Verify or validate a statement, belief, or fact", "example": "The scientist needed to confirm her hypothesis with further experiments."}, {"definition": "Prove the accuracy of an agreement or understanding between parties", "example": "They both agreed on the terms and then confirmed their commitment in writing."}, {"definition": "To provide a final answer that gives certainty to something previously uncertain", "example": "The doctor asked if I had any allergies, and after checking my medical history, she confirmed there were none."}, {"definition": "Reaffirm or strengthen an existing statement, belief, or decision", "example": "Despite the doubts of others, he wanted to confirm his love for her by proposing marriage."}, {"definition": "Give a formal declaration or approval", "example": "The judge confirmed that the defendant was guilty beyond a reasonable doubt."}]}