{"word": "qualified", "main_definition": "Having the necessary skills, knowledge or experience to do something effectively.", "meanings_and_examples": [{"definition": "Adjective - Lacking a degree of excellence; not fully competent or proficient in a certain area.", "example": "His claim to expertise was qualified at best, as he had only read about the subject."}, {"definition": "Adjective - Sufficiently skilled or educated to perform a particular task or job role effectively.", "example": "She is a highly qualified teacher with over 10 years of experience in education."}, {"definition": "Noun - A person who meets the necessary requirements for a job or professional position, often after an assessment or testing process.", "example": "The company has received several applications from highly qualified candidates for the managerial role."}, {"definition": "Verb (used with object) - To limit or restrict something to certain individuals who meet specific criteria.", "example": "The scholarship was qualified by requiring applicants to have a minimum GPA of 3.5."}]}