{"word": "extraction", "main_definition": "The process of removing or obtaining something, often from a larger source.", "meanings_and_examples": [{"definition": "Removing minerals or other substances from the earth.", "example": "Copper extraction involves digging deep underground mines and processing the ore."}, {"definition": "The act of obtaining information, usually through surveillance or interrogation.", "example": "During an investigation, law enforcement officers used extraction techniques to get confessions from suspects."}, {"definition": "Removing teeth, typically as a medical procedure.", "example": "The dentist performed the tooth extraction on my wisdom tooth that was causing pain."}, {"definition": "The act of drawing out or revealing something hidden or secret.", "example": "In literature, authors often use character development as a form of psychological extraction to uncover their motivations and desires."}, {"definition": "Removing data from digital devices for analysis purposes.", "example": "The security team conducted a mobile device extraction to retrieve deleted files from the suspect's smartphone."}]}