{"word": "hypothesis", "main_definition": "A hypothesis is a proposed explanation or educated guess that serves as the starting point for further investigation, experimentation, or study.", "meanings_and_examples": [{"definition": "In scientific research, it refers to an initial assumption made before conducting experiments and analyzing data", "example": "The scientist formulated a hypothesis that increased sunlight would accelerate the growth of plants."}, {"definition": "As an idea or theory suggesting something without firm evidence", "example": "He has a hypothesis that listening to classical music enhances concentration while studying."}, {"definition": "In logic and philosophy, it represents a tentative principle used in reasoning and argumentation", "example": "The philosopher proposed the hypothesis that all human actions are motivated by self-interest."}, {"definition": "As an alternative or counterargument to another perspective", "example": "She challenged her friend's hypothesis about climate change being solely caused by natural factors, suggesting that human activity plays a significant role too."}]}