{"word": "ISSN", "main_definition": "The International Standard Serial Number (ISSN) is an eight-digit code used to uniquely identify serial publications such as journals, magazines, and newspapers.", "meanings_and_examples": [{"definition": "A unique identifier for a periodical publication", "example": "The ISSN of 'Nature' journal is 0028-0836."}, {"definition": "An international standard code used in libraries and databases to catalog serial publications", "example": "To find the ISSN of a specific academic journal, one can search within library databases or directly from the publisher's website."}]}