{"word": "gallery", "main_definition": "A gallery is a space where artworks, such as paintings, photographs, or sculptures, are displayed for public viewing.", "meanings_and_examples": [{"definition": "An exhibition room for displaying works of art", "example": "The annual impressionist gallery showcased beautiful oil paintings and modern sculptures."}, {"definition": "A place where portraits or pictures are displayed", "example": "Visitors walked through the history gallery, admiring ancient maps and old photographs."}, {"definition": "A room in a building containing works of art", "example": "The children were amazed by the vibrant colors and shapes they saw at the modern art gallery."}, {"definition": "An area or collection of rooms designated for displaying objects, especially fine arts", "example": "The city's cultural district boasts a variety of galleries, each with its own unique focus on different types of artwork."}, {"definition": "A large hall used for the exhibition of works of art or curiosities", "example": "The natural history gallery was filled with dinosaur fossils and rare minerals."}]}