{"word": "com", "main_definition": "The abbreviation 'com' stands for 'community', often used in domain names to represent organizations, businesses, or communities.", "meanings_and_examples": [{"definition": "Short form of community", "example": "Many websites use the '.com' extension to denote that they are a part of an online community."}, {"definition": "A website or network address ending in .com indicating it is associated with businesses", "example": "www.apple.com refers to Apple Inc.'s official website, which is a company-oriented '.com' domain."}, {"definition": "Used as an abbreviation for 'commercial', referring to commercial activities or transactions", "example": "Commercial flights are those operated by airlines for the purpose of making profits, often denoted with a '.com' domain."}]}