{"word": "inc", "main_definition": "Inc is not a commonly used word or idiom in English, but it may be an abbreviation representing 'including' or related to the beginning of words like 'include'. However, there are no traditional meanings associated with just 'inc', so I will provide examples for 'including' and interpretations that might relate to the beginning of a phrase.", "meanings_and_examples": [{"definition": "Including", "example": "The package cost $10 inc shipping, which means it costs $10 plus additional charges for shipping."}, {"definition": "Beginning of a phrase indicating the presence of something else within a list or group", "example": "When purchasing items online, you may see prices listed with 'inc tax' to indicate that tax is included in the total price."}]}