{"word": "debt", "main_definition": "Debt is the state of owing money to someone else, or an obligation to repay borrowed funds.", "meanings_and_examples": [{"definition": "Amount of money that one party owes to another.", "example": "After purchasing his new car on credit, John's total debt reached $20,000."}, {"definition": "An obligation or responsibility to repay borrowed funds within a specified time frame.", "example": "The bank issued a loan of $15,000 with the condition that it must be paid back in five years."}, {"definition": "A financial liability resulting from excessive spending or borrowing beyond one's means.", "example": "By constantly charging on his credit card without repayment, Mike accumulated a significant debt that he couldn't manage."}, {"definition": "An investment vehicle consisting of bonds issued by corporations or governments to raise capital.", "example": "Many investors hold municipal bonds as a way to earn interest income while diversifying their portfolios."}]}