{"word": "random", "main_definition": "unpredictable or without a definite pattern, order, or method.", "meanings_and_examples": [{"definition": "causing something to happen without any reason or purpose:", "example": "The lottery numbers were completely random."}, {"definition": "unplanned or unforeseen occurrence that happens by chance, not due to a plan or design.", "example": "She met her future husband at a restaurant in what seemed like a totally random encounter."}, {"definition": "having no particular pattern or predictability; lacking order or method", "example": "The results of the experiment were completely random, making it impossible to draw any conclusions from them."}, {"definition": "selected by chance rather than intentionally:", "example": "A player chooses a card at random from a deck."}, {"definition": "lacking reason or purpose; haphazardly done or occurring without any pattern or system.", "example": "The artist's work is often praised for its seemingly random elements that create an unexpected beauty."}]}