{"word": "never", "main_definition": "Not at any time; not ever.", "meanings_and_examples": [{"definition": "Absolutely no chance or possibility of something happening", "example": "I will never forgive him for what he did."}, {"definition": "Not in a particular time period; not yet, at present", "example": "I have never tried sushi before."}, {"definition": "Utterly or completely against something", "example": "Never underestimate the power of love and kindness."}, {"definition": "In no way, shape, or form; without any doubt", "example": "She will never be able to do that on her own."}, {"definition": "Not used in a certain situation or context", "example": "I've never been good at public speaking."}]}