{"word": "Hindu", "main_definition": "A follower of Hinduism, a major religion originating from the Indian subcontinent or someone associated with this religion.", "meanings_and_examples": [{"definition": "Related to Hinduism or its adherents", "example": "Hindu rituals are performed during Diwali, a festival of lights."}, {"definition": "A person who follows the religion and cultural traditions of Hinduism", "example": "She is a devout Hindu who practices yoga daily and meditates regularly."}, {"definition": "Ethnic group native to India, often practicing Hinduism as their primary faith", "example": "The local community celebrates various Hindu festivals with great enthusiasm."}, {"definition": "Individuals or objects related to Indian culture and traditions, including the religious practices of Hinduism", "example": "The artwork in this gallery depicts scenes from ancient Hindu mythology."}]}