{"word": "treating", "main_definition": "Treating refers to the act of providing or offering something, such as food, drinks, or attention, typically in a generous or indulgent manner.", "meanings_and_examples": [{"definition": "To provide someone with food and drink", "example": "The restaurant was treating its guests to complimentary cocktails."}, {"definition": "To indulge or pamper (someone) by offering them pleasant experiences or gifts", "example": "She was treating her friends to a fancy dinner at an upscale restaurant."}, {"definition": "To present someone with something as payment or reward for their work, often in a casual or informal manner", "example": "The boss decided to treat the employees by taking them out for lunch."}, {"definition": "To apply (something) on or over a surface evenly and smoothly", "example": "He was treating his canvas with layers of paint to create an artistic effect."}]}