{"word": "membrane", "main_definition": "A thin, flexible layer or structure that separates or encloses different substances.", "meanings_and_examples": [{"definition": "In biology, a membrane is a thin, flexible barrier surrounding cells and compartments within them.", "example": "The cell membrane controls what enters and leaves the cell."}, {"definition": "An audio or visual filter that separates sound frequencies or colors, respectively.", "example": "A high-pass audio membrane filters out low frequencies from a sound recording."}, {"definition": "The thin layer of fluid surrounding an animal's eye, known as the lens.", "example": "The membrane in the human eye bends light rays to focus them on the retina."}, {"definition": "A structure found in certain organisms that acts like a stomach or storage compartment.", "example": "Cnidarians, such as jellyfish and corals, have specialized membranes called gastrovascular cavities."}, {"definition": "A thin layer of material used in various industries for lamination or coating.", "example": "The protective plastic wrapping is a type of synthetic membrane."}]}