{"word": "pete", "main_definition": "To dig or break into something, especially in a casual or informal manner.", "meanings_and_examples": [{"definition": "To excavate or break open (a hole) with physical effort.", "example": "After hours of peteing the ground for treasure, they found an old coin."}, {"definition": "To gain unauthorized access to a space, typically through force or deception.", "example": "The burglar managed to pete into the house by picking the lock on the front door."}, {"definition": "In slang, referring to having sexual intercourse.", "example": "They spent the night together and ended up getting it in the bedroom."}]}