[
    {
        "word": "announce",
        "word_hebrew": "להכריז",
        "main_definition": "To make a public or formal declaration about something, typically in advance of its occurrence.",
        "main_definition_hebrew": "להצהיר הצהרה פומבית או רשמית על משהו, בדרך כלל לפני התרחשותו.",
        "meanings_and_examples": [
            {
                "definition": "To declare or make known formally and officially",
                "definition_hebrew": "להכריז או להודיע באופן רשמי ורשמי",
                "example": "The company announced the launch of their new product at an event.",
                "example_hebrew": "החברה הודיעה על השקת המוצר החדש שלה באירוע."
            },
            {
                "definition": "To reveal information previously unknown or secret to a wider audience",
                "definition_hebrew": "לחשוף מידע שלא היה ידוע בעבר או סודי לקהל רחב יותר",
                "example": "She announced her engagement on social media with photos from the proposal.",
                "example_hebrew": "היא הכריזה על אירוסיה ברשתות החברתיות עם תמונות מההצעה."
            },
            {
                "definition": "To declare one's intention to do something, often in public",
                "definition_hebrew": "להצהיר על כוונתו לעשות משהו, לעתים קרובות בפומבי",
                "example": "The politician announced his candidacy for mayor during a press conference.",
                "example_hebrew": "הפוליטיקאי הכריז על מועמדותו לראשות העיר במהלך מסיבת עיתונאים."
            },
            {
                "definition": "To proclaim or make known the occurrence of an event, typically by stating it in advance",
                "definition_hebrew": "להכריז או להודיע על התרחשותו של אירוע, בדרך כלל על ידי הצהרה עליו מראש",
                "example": "The weatherman announced that there would be heavy snowfall overnight.",
                "example_hebrew": "איש מזג האוויר הודיע שיירד שלג כבד במהלך הלילה."
            }
        ]
    }
]