[
    {
        "word": "anytime",
        "word_hebrew": "בכל עת",
        "main_definition": "Anytime refers to at any given moment or whenever required, without specific restrictions.",
        "main_definition_hebrew": "כל זמן מתייחס בכל רגע נתון או מתי שנדרש, ללא הגבלות ספציפיות.",
        "meanings_and_examples": [
            {
                "definition": "Freely available and can be done at a convenient time for the individual.",
                "definition_hebrew": "זמין באופן חופשי וניתן לעשות זאת בזמן נוח לאדם.",
                "example": "You can call me anytime; I'm always here to help.",
                "example_hebrew": "אתה יכול להתקשר אלי בכל זמן; אני תמיד כאן כדי לעזור."
            },
            {
                "definition": "Ready or capable of being used whenever needed.",
                "definition_hebrew": "מוכן או ניתן לשימוש בכל עת שצריך.",
                "example": "This software is designed to run on multiple platforms and can be utilized anytime, anywhere.",
                "example_hebrew": "תוכנה זו נועדה לרוץ על מספר פלטפורמות וניתן להשתמש בה בכל זמן ובכל מקום."
            },
            {
                "definition": "At any moment; at no particular time or place in the future.",
                "definition_hebrew": "בכל רגע; בשום זמן או מקום מסוים בעתיד.",
                "example": "Feel free to reach out if you need assistance, we're here for you anytime.",
                "example_hebrew": "אל תהסס לפנות אם אתה צריך עזרה, אנחנו כאן בשבילך בכל עת."
            }
        ]
    }
]