[
    {
        "word": "cayman",
        "word_hebrew": "קיימן",
        "main_definition": "The Cayman Islands are a British Overseas Territory in the Caribbean, known primarily as an offshore financial center.",
        "main_definition_hebrew": "איי קיימן הם טריטוריה בריטית מעבר לים באיים הקריביים, הידועה בעיקר כמרכז פיננסי מהחוף.",
        "meanings_and_examples": [
            {
                "definition": "A type of predatory reptile",
                "definition_hebrew": "סוג של זוחל טורף",
                "example": "The cayman lizard is a large and powerful snake found in the tropical rainforests.",
                "example_hebrew": "לטאת הקיימן היא נחש גדול וחזק המצוי ביערות הגשם הטרופיים."
            },
            {
                "definition": "A unit of currency used in the Cayman Islands",
                "definition_hebrew": "יחידת מטבע המשמשת באיי קיימן",
                "example": "I need to exchange my US dollars for caymans before making purchases there.",
                "example_hebrew": "אני צריך להחליף את הדולר האמריקאי שלי לקיימן לפני ביצוע רכישות שם."
            },
            {
                "definition": "An idiomatic expression meaning a place or situation where one can operate with minimal risk or scrutiny",
                "definition_hebrew": "ביטוי אידיומטי פירושו מקום או מצב בו ניתן לפעול במינימום סיכון או בדיקה",
                "example": "This offshore bank account is considered the cayman of our financial activities.",
                "example_hebrew": "חשבון הבנק בחו\"ל זה נחשב לקיימן של הפעילות הפיננסית שלנו."
            }
        ]
    }
]