[
    {
        "word": "clear",
        "word_hebrew": "ברור",
        "main_definition": "To remove obstructions or haze, making something visible and understandable.",
        "main_definition_hebrew": "כדי להסיר חסימות או אובך, להפוך משהו לגלוי ומובן.",
        "meanings_and_examples": [
            {
                "definition": "Free from confusion; easy to perceive or understand.",
                "definition_hebrew": "נקי מבלבול; קל לתפיסה או הבנה.",
                "example": "The teacher's explanation was crystal clear.",
                "example_hebrew": "ההסבר של המורה היה ברור."
            },
            {
                "definition": "Not affected by something harmful or deceptive; pure and unadulterated.",
                "definition_hebrew": "לא מושפע ממשהו מזיק או מטעה; טהור ולא מזויף.",
                "example": "After the rain, the air felt so much clearer and fresher.",
                "example_hebrew": "אחרי הגשם, האוויר הרגיש הרבה יותר צלול ורענן."
            },
            {
                "definition": "Asking for a repetition or explanation to ensure understanding.",
                "definition_hebrew": "בקשת חזרה או הסבר כדי להבטיח הבנה.",
                "example": "I'm sorry, I didn't catch that. Could you please clear it up?",
                "example_hebrew": "אני מצטער, לא קלטתי את זה. תוכל בבקשה להבהיר את זה?"
            },
            {
                "definition": "To make visible by removing obstructions; to clarify or explain something thoroughly.",
                "definition_hebrew": "לעשות גלוי על ידי הסרת חסימות; להבהיר או להסביר משהו ביסודיות.",
                "example": "The instructor cleared her throat and explained the concept again.",
                "example_hebrew": "המדריכה כחכחה בגרונה והסבירה שוב את הרעיון."
            }
        ]
    }
]