[
    {
        "word": "excessive",
        "word_hebrew": "מוּפרָז",
        "main_definition": "Exceeding normal or reasonable limits; going beyond what is necessary, appropriate, or allowed.",
        "main_definition_hebrew": "חריגה מהגבולות הרגילים או הסבירים; מעבר למה שצריך, מתאים או מותר.",
        "meanings_and_examples": [
            {
                "definition": "Beyond the usual or appropriate amount",
                "definition_hebrew": "מעבר לכמות הרגילה או המתאימה",
                "example": "She applied excessive makeup for her wedding day.",
                "example_hebrew": "היא איפרה יתר על המידה ליום חתונתה."
            },
            {
                "definition": "Unreasonably large in size, quantity, or intensity",
                "definition_hebrew": "גדול באופן בלתי סביר בגודל, בכמות או בעוצמה",
                "example": "He was taking an excessively high dosage of painkillers.",
                "example_hebrew": "הוא נטל מינון גבוה מדי של משככי כאבים."
            },
            {
                "definition": "Going too far in one's actions or behavior",
                "definition_hebrew": "ללכת רחוק מדי במעשיו או בהתנהגותו",
                "example": "His anger towards his boss had become excessive, leading him to storm out of the office.",
                "example_hebrew": "הכעס שלו כלפי הבוס שלו הפך מוגזם, מה שהוביל אותו לצאת בסערה מהמשרד."
            },
            {
                "definition": "More than what is considered normal or necessary",
                "definition_hebrew": "יותר ממה שנחשב נורמלי או הכרחי",
                "example": "Their consumption of sugar was excessive compared to other families' habits.",
                "example_hebrew": "צריכת הסוכר שלהם הייתה מוגזמת בהשוואה להרגלים של משפחות אחרות."
            },
            {
                "definition": "Abnormally high in quantity, degree, or size; more than ordinarily",
                "definition_hebrew": "גבוה באופן חריג בכמות, בדרגה או בגודל; יותר מהרגיל",
                "example": "During the heatwave, they were drinking water in excessive amounts to stay hydrated.",
                "example_hebrew": "במהלך גל החום, הם שתו מים בכמויות מוגזמות כדי להישאר לחות."
            }
        ]
    }
]