[
    {
        "word": "imposed",
        "word_hebrew": "מוטל",
        "main_definition": "To impose something means to force or dictate it upon someone or something, usually without their consent.",
        "main_definition_hebrew": "לכפות משהו פירושו לכפות או להכתיב אותו על מישהו או משהו, בדרך כלל ללא הסכמתו.",
        "meanings_and_examples": [
            {
                "definition": "Forcing a rule, law, or regulation on others.",
                "definition_hebrew": "כפיית כלל, חוק או תקנה על אחרים.",
                "example": "The government imposed new taxes on imported goods to protect local businesses.",
                "example_hebrew": "הממשלה הטילה מסים חדשים על סחורות מיובאות כדי להגן על עסקים מקומיים."
            },
            {
                "definition": "Making someone do something they don't want to do.",
                "definition_hebrew": "לגרום למישהו לעשות משהו שהוא לא רוצה לעשות.",
                "example": "After much persuasion, the children reluctantly agreed to finish their homework before playing.",
                "example_hebrew": "לאחר שכנועים רבים, הילדים הסכימו באי רצון לסיים את שיעורי הבית שלהם לפני המשחק."
            },
            {
                "definition": "Demanding or expecting certain behavior from others.",
                "definition_hebrew": "דורש או מצפה להתנהגות מסוימת מאחרים.",
                "example": "The teacher imposed strict classroom rules to maintain discipline among students.",
                "example_hebrew": "המורה הטילה חוקים מחמירים בכיתה כדי לשמור על משמעת בקרב התלמידים."
            },
            {
                "definition": "To establish a standard, guideline, or policy that must be followed.",
                "definition_hebrew": "לקבוע תקן, קו מנחה או מדיניות שיש לפעול לפיהם.",
                "example": "The company's CEO decided to impose a new dress code for all employees starting next month.",
                "example_hebrew": "מנכ\"ל החברה החליט להטיל קוד לבוש חדש לכל העובדים החל מהחודש הבא."
            }
        ]
    }
]