[
    {
        "word": "mod",
        "word_hebrew": "mod",
        "main_definition": "To modify or adjust something according to personal taste or current trends.",
        "main_definition_hebrew": "לשנות או להתאים משהו לפי הטעם האישי או הטרנדים הנוכחיים.",
        "meanings_and_examples": [
            {
                "definition": "Trendy or fashionable, especially in reference to clothing and accessories.",
                "definition_hebrew": "טרנדי או אופנתי, במיוחד בהתייחסות ללבוש ואביזרים.",
                "example": "She prefers a mod look with her vintage dresses.",
                "example_hebrew": "היא מעדיפה מראה מוד עם שמלות הוינטג' שלה."
            },
            {
                "definition": "To make changes or adjustments to something, often in the context of technology or design.",
                "definition_hebrew": "לבצע שינויים או התאמות למשהו, לעתים קרובות בהקשר של טכנולוגיה או עיצוב.",
                "example": "I had to mod my computer's software for it to work properly.",
                "example_hebrew": "הייתי צריך לשנות את התוכנה של המחשב שלי כדי שזה יעבוד כמו שצריך."
            },
            {
                "definition": "A preference for a certain type of music known as Mod culture or 'Mod subculture', originating from British youth in the 1960s.",
                "definition_hebrew": "העדפה לסוג מסוים של מוזיקה המכונה Mod culture או 'Mod subculture', שמקורה בנוער בריטי בשנות ה-60.",
                "example": "The band embraced their mod identity, inspired by the original Mod movement.",
                "example_hebrew": "הלהקה אימצה את זהות המוד שלה, בהשראת תנועת המוד המקורית."
            }
        ]
    }
]