[
    {
        "word": "ooo",
        "word_hebrew": "אוו",
        "main_definition": "The phrase 'ooo' is an exclamation commonly used to express surprise, disappointment or disapproval.",
        "main_definition_hebrew": "הביטוי 'אוו' הוא קריאה נפוץ להבעת הפתעה, אכזבה או אי הסכמה.",
        "meanings_and_examples": [
            {
                "definition": "Expressing disbelief or shock",
                "definition_hebrew": "הבעת חוסר אמון או הלם",
                "example": "I can't believe we lost the game! Ooo.",
                "example_hebrew": "אני לא מאמין שהפסדנו את המשחק! אוו."
            },
            {
                "definition": "Conveying disappointment or disapproval",
                "definition_hebrew": "העברת אכזבה או אי הסכמה",
                "example": "Oh no, you ate all my cookies again? Ooo!",
                "example_hebrew": "הו לא, שוב אכלת את כל העוגיות שלי? אוו!"
            }
        ]
    }
]