[
    {
        "word": "quebec",
        "word_hebrew": "קוויבק",
        "main_definition": "Quebec is a province in eastern Canada, known for its French-speaking culture and history.",
        "main_definition_hebrew": "קוויבק הוא מחוז במזרח קנדה, הידוע בתרבות ובהיסטוריה של דוברי הצרפתית.",
        "meanings_and_examples": [
            {
                "definition": "A Canadian province",
                "definition_hebrew": "מחוז קנדי",
                "example": "I visited Quebec last summer. It's the only officially bilingual province in Canada.",
                "example_hebrew": "ביקרתי בקיץ שעבר בקוויבק. זהו המחוז הדו-לשוני היחיד בקנדה."
            },
            {
                "definition": "The French-speaking region of Canada",
                "definition_hebrew": "האזור דובר הצרפתית של קנדה",
                "example": "Quebecois culture and language are distinct from English-speaking parts of Canada.",
                "example_hebrew": "התרבות והשפה של קוויבק נבדלות מחלקים דוברי אנגלית בקנדה."
            },
            {
                "definition": "A former name for the city of Quebec, which is now called Quebec City",
                "definition_hebrew": "שם לשעבר לעיר קוויבק, שנקראת כיום קוויבק סיטי",
                "example": "The historic Old Town of Quebec is located within Quebec City. It's a UNESCO World Heritage site.",
                "example_hebrew": "העיר העתיקה ההיסטורית של קוויבק ממוקמת בתוך קוויבק סיטי. זהו אתר מורשת עולמית של אונסק\"ו."
            }
        ]
    }
]