[
    {
        "word": "raymond",
        "word_hebrew": "ריימונד",
        "main_definition": "A common name, typically used as a given name or nickname, derived from the Old French form of Roland.",
        "main_definition_hebrew": "שם נפוץ, המשמש בדרך כלל כשם פרטי או כינוי, שנגזר מהצורה הצרפתית העתיקה של רולנד.",
        "meanings_and_examples": [
            {
                "definition": "A male first name derived from the Old French form of Roland, which in turn originated from the Frankish name Raginbert. It means 'rage' or 'fiery protector'.",
                "definition_hebrew": "שם פרטי זכרי שנגזר מהצורה הצרפתית הישנה של רולנד, שמקורה בתורו מהשם הפרנקי Raginbert. זה אומר 'זעם' או 'מגן לוהט'.",
                "example": "My friend Raymond is named after his grandfather who was a brave warrior.",
                "example_hebrew": "חברי ריימונד נקרא על שם סבו שהיה לוחם אמיץ."
            },
            {
                "definition": "A nickname often used as an affectionate term for someone whose name starts with 'Ray', similar to other pet names like 'Buddy' or 'Pal'.",
                "definition_hebrew": "כינוי המשמש לעתים קרובות כמונח חיבה למישהו ששמו מתחיל ב'ריי', בדומה לשמות חיות מחמד אחרים כמו 'באדי' או 'חבר'.",
                "example": "My friend calls his older brother Raymond, but he always refers to him as Ray.",
                "example_hebrew": "חבר שלי קורא לאחיו הגדול ריימונד, אבל הוא תמיד מתייחס אליו כריי."
            },
            {
                "definition": "A surname derived from the given name 'Raymond'. This is less common than its use as a first name.",
                "definition_hebrew": "שם משפחה שנגזר מהשם הפרטי 'ריימונד'. זה פחות נפוץ מהשימוש בו כשם פרטי.",
                "example": "John and Mary's son was named Raymond after his great-grandfather. Now, their last name is Raymond.",
                "example_hebrew": "בנם של ג'ון ומרי נקרא ריימונד על שם סבו רבא. עכשיו, שם המשפחה שלהם הוא ריימונד."
            },
            {
                "definition": "A fictional character from literature or media that shares the name 'Raymond'.",
                "definition_hebrew": "דמות בדיונית מספרות או תקשורת החולקת את השם 'ריימונד'.",
                "example": "In the movie 'The Princess Bride', there's a character named Count Rugen, also known as Rayfione.",
                "example_hebrew": "בסרט 'כלת הנסיכה', יש דמות בשם הרוזן רוגן, הידועה גם בשם רייפיונה."
            }
        ]
    }
]