[
    {
        "word": "regulatory",
        "word_hebrew": "רגולטורים",
        "main_definition": "Relating to the rules, control measures, or authority that governs an activity, industry, or organization.",
        "main_definition_hebrew": "בהתייחס לכללים, לאמצעי בקרה או לסמכות השולטים בפעילות, בתעשייה או בארגון.",
        "meanings_and_examples": [
            {
                "definition": "Pertaining to government regulations and laws.",
                "definition_hebrew": "בקשר לתקנות וחוקים ממשלתיים.",
                "example": "The company's operations are highly influenced by environmental regulatory requirements.",
                "example_hebrew": "פעילות החברה מושפעת מאוד מדרישות רגולטוריות סביבתיות."
            },
            {
                "definition": "Involving the oversight or supervision of an industry, business, or activity.",
                "definition_hebrew": "כרוך בפיקוח או פיקוח על תעשייה, עסק או פעילות.",
                "example": "Regulatory agencies monitor financial markets to ensure fair practices.",
                "example_hebrew": "סוכנויות רגולטוריות עוקבות אחר השווקים הפיננסיים כדי להבטיח נהלים הוגנים."
            },
            {
                "definition": "Relating to the process of establishing rules and guidelines for a particular area or field.",
                "definition_hebrew": "התייחסות לתהליך קביעת כללים והנחיות לתחום או תחום מסוים.",
                "example": "The new regulatory framework was designed to protect consumers in the tech industry.",
                "example_hebrew": "המסגרת הרגולטורית החדשה נועדה להגן על צרכנים בתעשיית הטכנולוגיה."
            },
            {
                "definition": "Involving an organization responsible for enforcing laws, standards, or regulations within a specific domain.",
                "definition_hebrew": "מעורבות ארגון שאחראי לאכיפת חוקים, תקנים או תקנות בתחום מסוים.",
                "example": "Regulatory bodies often conduct inspections and audits to ensure compliance with industry standards.",
                "example_hebrew": "גופים רגולטוריים מבצעים לעתים קרובות בדיקות וביקורות כדי להבטיח עמידה בתקנים בתעשייה."
            },
            {
                "definition": "Describing the act of implementing control measures or restrictions on certain actions or behaviors.",
                "definition_hebrew": "תיאור הפעולה של יישום אמצעי בקרה או הגבלות על פעולות או התנהגויות מסוימות.",
                "example": "The regulatory action was taken against the company for violating environmental laws.",
                "example_hebrew": "הפעולה הרגולטורית ננקטה נגד החברה בגין הפרת חוקי איכות הסביבה."
            }
        ]
    }
]