[
    {
        "word": "silly",
        "word_hebrew": "טִפּשִׁי",
        "main_definition": "Silly refers to actions or behavior that are not serious, lacking in common sense, or amusingly foolish.",
        "main_definition_hebrew": "טיפשי מתייחס לפעולות או התנהגות שאינן רציניות, חסרות שכל ישר או טיפשיות באופן משעשע.",
        "meanings_and_examples": [
            {
                "definition": "playful and fun-loving",
                "definition_hebrew": "שובב ואוהב כיף",
                "example": "The children's silly antics made everyone laugh.",
                "example_hebrew": "התעלולים המטופשים של הילדים הצחיקו את כולם."
            },
            {
                "definition": "lacking common sense or good judgment",
                "definition_hebrew": "חסר שכל ישר או שיקול דעת טוב",
                "example": "She wore a costume to the office, which was quite silly given the formal work environment.",
                "example_hebrew": "היא לבשה תחפושת למשרד, מה שהיה די מטופש בהתחשב בסביבת העבודה הרשמית."
            },
            {
                "definition": "amusingly foolish",
                "definition_hebrew": "טיפשי בצורה משעשעת",
                "example": "The comedian's silliness on stage had the audience in stitches.",
                "example_hebrew": "הטיפשות של הקומיקאי על הבמה גרמה לקהל תפרים."
            },
            {
                "definition": "naive or easily influenced",
                "definition_hebrew": "נאיבי או מושפע בקלות",
                "example": "His naive trust of strangers made him susceptible to scams, a somewhat silly approach for his safety.",
                "example_hebrew": "האמון הנאיבי שלו בזרים גרם לו להיות חשוף להונאות, גישה טיפשית משהו למען ביטחונו."
            }
        ]
    }
]