{"word": "customize", "main_definition": "To modify or alter something according to specific preferences, requirements, or needs.", "meanings_and_examples": [{"definition": "Adjusting a product's features based on individual preference.", "example": "I want to customize my car by adding a spoiler and upgrading the sound system."}, {"definition": "Personalizing an experience or service to match specific needs.", "example": "The online store allows you to customize your product order, choosing different colors and materials."}, {"definition": "Creating a tailored solution for software development by incorporating unique requirements.", "example": "We need to customize the existing e-commerce application to handle our inventory management system efficiently."}, {"definition": "Modifying or altering an item's design, appearance, or functionality based on user preferences.", "example": "I would like to customize my phone with a new case and wallpaper."}, {"definition": "Adapting content or presentations to suit the audience or event specifics.", "example": "The speaker customized his presentation for different audiences, including one focusing on marketing strategies."}]}