{"word": "Iraqi", "main_definition": "Related to or originating from Iraq, a country in the Middle East.", "meanings_and_examples": [{"definition": "A person native to Iraq or of Iraqi descent.", "example": "Sara is an Iraqi who was born and raised in Baghdad."}, {"definition": "Relating to the culture, customs, or products of Iraq.", "example": "Iraqi cuisine features a rich blend of spices and flavors typical of Middle Eastern food."}, {"definition": "Pertaining to the political situation in Iraq, especially concerning its government and conflicts.", "example": "The ongoing tension between different ethnic groups within Iraq continues to shape the country's politics."}]}