{"word": "sight", "main_definition": "Sight refers to the ability to see, a visual perception or an instance of something being seen.", "meanings_and_examples": [{"definition": "The act of seeing or viewing something with one's eyes", "example": "The breathtaking sight of Niagara Falls left visitors in awe."}, {"definition": "A natural scenery or landscape worth observing and admiring", "example": "We went on a trip to see the majestic mountains as a wonderful sight."}, {"definition": "An opportunity, event, or experience that is seen as remarkable or noteworthy", "example": "The inauguration of the new president was a significant historical sight."}, {"definition": "A person who can see well, someone with good eyesight", "example": "My grandfather had excellent sight and could read even fine print without glasses."}, {"definition": "The legal right to witness a particular event or process", "example": "I have the sight of attending every trial because I am a journalist."}]}