{"word": "oaks", "main_definition": "Oaks refer to a type of tree belonging to the genus Quercus, known for their strong wood and long-lived nature. Additionally, 'oaks' can be an idiomatic expression related to individuals who are considered highly skilled or respected in their field.", "meanings_and_examples": [{"definition": "Type of tree belonging to the genus Quercus", "example": "The ancient oaks stood tall and proud, marking the passage of time."}, {"definition": "Idiomatic expression for individuals who are highly skilled or respected in their field", "example": "She is an oak among apprentices, always leading by example with her vast knowledge."}]}