{"word": "welding", "main_definition": "Welding is a fabrication process that joins materials, usually metals or thermoplastics, by causing coalescence.", "meanings_and_examples": [{"definition": "A form of labor involving the joining of metal pieces using heat and pressure", "example": "The welder carefully fused two steel plates together to create a strong joint."}, {"definition": "An idiomatic expression meaning to combine or unite different elements into one cohesive whole", "example": "They were able to weld the team's diverse skills and perspectives into a successful project outcome."}]}